sersir/__init__.py
sersir/__main__.py
sersir/base/__init__.py
sersir/base/runner.py
sersir/base/settings.py
sersir/jenkins/__init__.py
sersir/jenkins/requests.py
sersir/utils/__init__.py
sersir/utils/setting_helper.py
sersir-0.2.1.dist-info/DESCRIPTION.rst
sersir-0.2.1.dist-info/METADATA
sersir-0.2.1.dist-info/RECORD
sersir-0.2.1.dist-info/WHEEL
sersir-0.2.1.dist-info/metadata.json
sersir-0.2.1.dist-info/top_level.txt
sersir-0.2.1.dist-info/zip-safe
