Metadata-Version: 2.0
Name: sersir
Version: 0.2.1
Summary: server siren - failed jenkins job activates a gpio pin / siren
Home-page: https://bitbucket.org/icconsult/sersir
Author: Christian Kohlstedde
Author-email: christian.kohlstedde@ic-consult.de
License: MIT
Keywords: Raspberry Pi gpio jenkins
Platform: UNKNOWN
Classifier: License :: OSI Approved :: MIT License
Classifier: Programming Language :: Python :: 3
Classifier: Intended Audience :: Developers
Classifier: Operating System :: POSIX :: Linux
Classifier: Development Status :: 4 - Beta
Requires-Dist: RPi.GPIO
Provides-Extra: systemd
Requires-Dist: systemd; extra == 'systemd'
